odoo/addons/account_payment_promissory_note/README.rst
odoo/addons/account_payment_promissory_note/__init__.py
odoo/addons/account_payment_promissory_note/__manifest__.py
odoo/addons/account_payment_promissory_note/i18n/account_payment_promissory_note.pot
odoo/addons/account_payment_promissory_note/i18n/es.po
odoo/addons/account_payment_promissory_note/models/__init__.py
odoo/addons/account_payment_promissory_note/models/account_abstract_payment.py
odoo/addons/account_payment_promissory_note/models/account_payment.py
odoo/addons/account_payment_promissory_note/readme/CONTRIBUTORS.rst
odoo/addons/account_payment_promissory_note/readme/DESCRIPTION.rst
odoo/addons/account_payment_promissory_note/readme/USAGE.rst
odoo/addons/account_payment_promissory_note/static/description/icon.png
odoo/addons/account_payment_promissory_note/static/description/index.html
odoo/addons/account_payment_promissory_note/tests/__init__.py
odoo/addons/account_payment_promissory_note/tests/test_account_payment_promissory_note.py
odoo/addons/account_payment_promissory_note/views/account_payment_invoice_view.xml
odoo/addons/account_payment_promissory_note/views/account_payment_view.xml
odoo/addons/account_payment_promissory_note/wizard/__init__.py
odoo/addons/account_payment_promissory_note/wizard/account_register_payments.py
odoo13_addon_account_payment_promissory_note-13.0.1.1.1.dist-info/METADATA
odoo13_addon_account_payment_promissory_note-13.0.1.1.1.dist-info/WHEEL
odoo13_addon_account_payment_promissory_note-13.0.1.1.1.dist-info/top_level.txt
odoo13_addon_account_payment_promissory_note-13.0.1.1.1.dist-info/RECORD
